[	
	{
		"conditions" : 
			{ 
				"tag" : "planet_pop_large",
				"owner" : "Clans",
				"rep" : ">liked"
			},
		"items" : "RT_List_Clan_Major"
	},
	{
		"conditions" : 
			{ 
				"tag" : "planet_pop_small",
				"owner" : "Clans",
				"rep" : ">liked"
			},
		"items" : "RT_List_Clan_Minor"
	},
	{
		"conditions" : 
			{ 
				"tag" : "planet_pop_medium, planet_civ_innersphere",
				"owner" : "Clans",
				"rep" : ">liked"
			},
		"items" : "RT_List_Clan_Major"
	},
	{
		"conditions" : 
			{ 
				"tag" : "planet_pop_medium, !planet_civ_innersphere",
				"owner" : "Clans",
				"rep" : ">liked"
			},
		"items" : "RT_List_Clan_Minor"
	},
	{
		"conditions" : 
			{ 
				"tag" : "planet_pop_large",
				"owner" : "Clans",
				"rep" : ">FRIENDLY"
			},
		"items" : "RT_List_Clan_Major"
	},
	{
		"conditions" : 
			{ 
				"tag" : "planet_pop_large",
				"owner" : "Clans",
				"rep" : "HONORED"
			},
		"items" : "RT_List_Clan_Major"
	}
]